anon/__init__.py
anon/atom.py
anon/conf.py
anon/diff.py
anon/dual.py
anon/hist.py
anon/lila.py
anon/poly.py
anon/quad.py
anon/quad_simplex.py
anon/step.py
anon/core/__init__.py
anon/core/assm.py
anon/core/interfaces.py
anon-0.0.1.dist-info/METADATA
anon-0.0.1.dist-info/WHEEL
anon-0.0.1.dist-info/top_level.txt
anon-0.0.1.dist-info/RECORD
